jiratui/__init__.py
jiratui/api/__init__.py
jiratui/api/api.py
jiratui/api/client.py
jiratui/api/tests/__init__.py
jiratui/api/tests/responses/assignable_users_search.json
jiratui/api/tests/responses/evaluate_expression.json
jiratui/api/tests/responses/issue.json
jiratui/api/tests/responses/issue_remote_links.json
jiratui/api/tests/responses/project.json
jiratui/api/tests/responses/project_statuses.json
jiratui/api/tests/responses/statuses.json
jiratui/api/tests/test_api.py
jiratui/api/tests/test_client.py
jiratui/api/tests/test_utils.py
jiratui/api/utils.py
jiratui/api_controller/__init__.py
jiratui/api_controller/constants.py
jiratui/api_controller/controller.py
jiratui/api_controller/factories.py
jiratui/api_controller/tests/__init__.py
jiratui/api_controller/tests/responses/issue.json
jiratui/api_controller/tests/responses/issue_no_adf.json
jiratui/api_controller/tests/responses/issue_remote_links.json
jiratui/api_controller/tests/test_controller.py
jiratui/api_controller/tests/test_factories.py
jiratui/app.py
jiratui/cli.py
jiratui/commands/__init__.py
jiratui/commands/handler.py
jiratui/commands/render.py
jiratui/config.py
jiratui/conftest.py
jiratui/constants.py
jiratui/css/jt.tcss
jiratui/exceptions.py
jiratui/files.py
jiratui/models.py
jiratui/tests/__init__.py
jiratui/tests/test_app.py
jiratui/tests/test_attachments.py
jiratui/tests/test_fulltext_search.py
jiratui/tests/test_git.py
jiratui/tests/test_main_screen.py
jiratui/tests/test_search_results.py
jiratui/tests/test_widgets.py
jiratui/utils/__init__.py
jiratui/utils/adf2md/__init__.py
jiratui/utils/adf2md/adf2md.py
jiratui/utils/adf2md/markdown.py
jiratui/utils/adf2md/nodes.py
jiratui/utils/adf2md/tests/__init__.py
jiratui/utils/adf2md/tests/test_adf_to_markdown.py
jiratui/utils/create_work_item.py
jiratui/utils/in_app_help.md
jiratui/utils/mime.py
jiratui/utils/styling.py
jiratui/utils/test_utilities.py
jiratui/utils/tests/__init__.py
jiratui/utils/tests/test_styling.py
jiratui-1.4.0.dist-info/WHEEL
jiratui-1.4.0.dist-info/entry_points.txt
jiratui-1.4.0.dist-info/METADATA
jiratui-1.4.0.dist-info/RECORD
