Metadata-Version: 2.3
Name: jiratui
Version: 1.4.0
Summary: A TUI for interacting with Atlassian Jira from your terminal.
Keywords: tui,jira,cli,terminal,shell,task-management
Author: Gaston T.
Author-email: Gaston T. <pythondeveloper@outlook.com>
Classifier: Development Status :: 5 - Production/Stable
Classifier: Environment :: Console
Classifier: Framework :: AsyncIO
Classifier: Framework :: Pydantic :: 2
Classifier: Framework :: Pytest
Classifier: Framework :: Sphinx
Classifier: Intended Audience :: Developers
Classifier: Operating System :: OS Independent
Classifier: Programming Language :: Python :: 3.10
Classifier: Programming Language :: Python :: 3.11
Classifier: Programming Language :: Python :: 3.12
Classifier: Programming Language :: Python :: 3.13
Classifier: Programming Language :: Python :: Implementation :: CPython
Classifier: Topic :: Terminals
Classifier: Topic :: Utilities
Requires-Dist: click==8.3.0
Requires-Dist: gitpython>=3.1.45
Requires-Dist: httpx>=0.28.1
Requires-Dist: pydantic-settings[yaml]>=2.11.0
Requires-Dist: python-dateutil>=2.9.0.post0
Requires-Dist: python-json-logger>=4.0.0
Requires-Dist: python-magic>=0.4.27
Requires-Dist: textual-image>=0.8.4
Requires-Dist: textual[syntax]>=6.4.0
Requires-Dist: xdg-base-dirs>=6.0.2
Maintainer: Gaston T.
Maintainer-email: Gaston T. <pythondeveloper@outlook.com>
Requires-Python: >=3.10, <3.14
Project-URL: Changelog, https://github.com/whyisdifficult/jiratui/blob/main/CHANGELOG.md
Project-URL: Documentation, https://jiratui.readthedocs.io/en/latest/index.html
Project-URL: Homepage, https://jiratui.sh
Project-URL: Issues, https://github.com/whyisdifficult/jiratui/issues
Project-URL: Repository, https://github.com/whyisdifficult/jiratui
